veracross_api3/__init__.py
veracross_api3/veracross_api3.py
veracross_api3-0.0.5.dist-info/METADATA
veracross_api3-0.0.5.dist-info/WHEEL
veracross_api3-0.0.5.dist-info/licenses/LICENSE
veracross_api3-0.0.5.dist-info/RECORD
