Metadata-Version: 2.3
Name: veracross_api3
Version: 0.0.5
Summary: Simple library for interacting with the Veracross API
Project-URL: Homepage, https://github.com/beckf/veracross_api3/
Project-URL: Issues, https://github.com/beckf/veracross_api3/issues
Author-email: Forrest Beck <forrest.beck@gmail.com>
Classifier: License :: OSI Approved :: MIT License
Classifier: Operating System :: OS Independent
Classifier: Programming Language :: Python :: 3
Requires-Python: >=3.8
